django_bird/__init__.py
django_bird/_typing.py
django_bird/apps.py
django_bird/components.py
django_bird/conf.py
django_bird/manifest.py
django_bird/params.py
django_bird/py.typed
django_bird/staticfiles.py
django_bird/templates.py
django_bird/urls.py
django_bird/utils.py
django_bird/views.py
django_bird/management/__init__.py
django_bird/management/commands/__init__.py
django_bird/management/commands/generate_asset_manifest.py
django_bird/plugins/__init__.py
django_bird/plugins/hookspecs.py
django_bird/plugins/manager.py
django_bird/templatetags/__init__.py
django_bird/templatetags/django_bird.py
django_bird/templatetags/tags/__init__.py
django_bird/templatetags/tags/asset.py
django_bird/templatetags/tags/bird.py
django_bird/templatetags/tags/prop.py
django_bird/templatetags/tags/slot.py
django_bird/templatetags/tags/var.py
django_bird-0.17.3.dist-info/METADATA
django_bird-0.17.3.dist-info/WHEEL
django_bird-0.17.3.dist-info/licenses/AUTHORS.md
django_bird-0.17.3.dist-info/licenses/LICENSE
django_bird-0.17.3.dist-info/RECORD
