Metadata-Version: 2.4
Name: django-bird
Version: 0.17.3
Summary: High-flying components for perfectionists with deadlines
Project-URL: Documentation, https://django-bird.readthedocs.io/
Project-URL: Issues, https://github.com/joshuadavidthomas/django-bird/issues
Project-URL: Source, https://github.com/joshuadavidthomas/django-bird
Author-email: Josh Thomas <josh@joshthomas.dev>
License: MIT License
License-File: AUTHORS.md
License-File: LICENSE
Classifier: Development Status :: 4 - Beta
Classifier: Framework :: Django
Classifier: Framework :: Django :: 4.2
Classifier: Framework :: Django :: 5.0
Classifier: Framework :: Django :: 5.1
Classifier: Framework :: Django :: 5.2
Classifier: License :: OSI Approved :: MIT License
Classifier: Operating System :: OS Independent
Classifier: Programming Language :: Python
Classifier: Programming Language :: Python :: 3
Classifier: Programming Language :: Python :: 3 :: Only
Classifier: Programming Language :: Python :: 3.10
Classifier: Programming Language :: Python :: 3.11
Classifier: Programming Language :: Python :: 3.12
Classifier: Programming Language :: Python :: 3.13
Classifier: Programming Language :: Python :: Implementation :: CPython
Requires-Python: >=3.10
Requires-Dist: django>=4.2
Requires-Dist: pluggy>=1.5.0
